musclepy/__init__.py
musclepy/femodel/__init__.py
musclepy/femodel/prestress_scenario.py
musclepy/femodel/pyelements.py
musclepy/femodel/pynodes.py
musclepy/femodel/pytruss.py
musclepy/solvers/__init__.py
musclepy/solvers/dm/__init__.py
musclepy/solvers/dm/linear_dm.py
musclepy/solvers/dm/nonlinear_dm.py
musclepy/solvers/dr/__init__.py
musclepy/solvers/dr/main.py
musclepy/solvers/dr/py_config_dr.py
musclepy/solvers/dr/py_elements_dr.py
musclepy/solvers/dr/py_nodes_dr.py
musclepy/solvers/dr/py_truss_dr.py
musclepy/solvers/selfstress/__init__.py
musclepy/solvers/selfstress/modes.py
musclepy/solvers/svd/__init__.py
musclepy/solvers/svd/main.py
musclepy/solvers/svd/py_results_svd.py
musclepy/solvers/test/__init__.py
musclepy/solvers/test/test_script.py
musclepy/utils/__init__.py
musclepy/utils/matrix_calculations.py
musclepy-1.0.0.dist-info/METADATA
musclepy-1.0.0.dist-info/WHEEL
musclepy-1.0.0.dist-info/licenses/COPYING.txt
musclepy-1.0.0.dist-info/RECORD
