Metadata-Version: 2.4
Name: musclepy
Version: 1.0.0
Summary: MusclePy is a Python package for structural analysis that focuses on the design, analysis, and optimization of tensegrity, tension-based, and truss-like structures.
Project-URL: source, https://github.com/JonasFeron/Muscle
Project-URL: issues, https://github.com/JonasFeron/Muscle/issues
Author-email: "Jonas FERON - Université catholique de Louvain (UCLouvain)" <pierre.latteur@uclouvain.be>
License-Expression: Apache-2.0
License-File: COPYING.txt
Classifier: Operating System :: OS Independent
Classifier: Programming Language :: Python :: 3
Classifier: Topic :: Scientific/Engineering :: Mathematics
Classifier: Topic :: Scientific/Engineering :: Physics
Requires-Python: >=3.9
Requires-Dist: numpy>=1.26.4
Requires-Dist: scipy>=1.13.1
